LICENSE.txt
MANIFEST.in
README.rst
requirements.txt
setup.py
setupegg.py
tox.ini
doc/Makefile
doc/postprocess.py
doc/rtd-pip-requirements.txt
doc/release/0.3.0-notes.rst
doc/source/apps.nanogen_gui.rst
doc/source/apps.rst
doc/source/conf.py
doc/source/contribute.rst
doc/source/core.atoms.rst
doc/source/core.crystallography.rst
doc/source/core.geometric_regions.rst
doc/source/core.math.rst
doc/source/core.molecules.rst
doc/source/core.physics.rst
doc/source/core.refdata.rst
doc/source/core.rst
doc/source/credits.rst
doc/source/data.rst
doc/source/generators.rst
doc/source/getting_started.rst
doc/source/index.rst
doc/source/io.rst
doc/source/release.0.3.0.rst
doc/source/release.rst
doc/source/scripts.nanogen.rst
doc/source/scripts.nanogenui.rst
doc/source/scripts.rst
doc/source/structures.rst
doc/source/testing.rst
doc/source/utils.analysis.rst
doc/source/utils.rst
doc/source/utils.symmetry_groups.rst
doc/source/tutorial/analysis.rst
doc/source/tutorial/examples.rst
doc/source/tutorial/generators.rst
doc/source/tutorial/index.rst
doc/source/tutorial/scripts.rst
scikit_nano.egg-info/PKG-INFO
scikit_nano.egg-info/SOURCES.txt
scikit_nano.egg-info/dependency_links.txt
scikit_nano.egg-info/entry_points.txt
scikit_nano.egg-info/not-zip-safe
scikit_nano.egg-info/pbr.json
scikit_nano.egg-info/requires.txt
scikit_nano.egg-info/top_level.txt
sknano/__init__.py
sknano/setup.py
sknano/version.py
sknano/apps/__init__.py
sknano/apps/setup.py
sknano/apps/nanogen_gui/__init__.py
sknano/apps/nanogen_gui/_nanogen_controllers.py
sknano/apps/nanogen_gui/_nanogen_models.py
sknano/apps/nanogen_gui/_nanogen_views.py
sknano/apps/nanogen_gui/_pyqt4_ui_bulk_structure_generator.py
sknano/apps/nanogen_gui/_pyqt4_ui_fullerene_generator.py
sknano/apps/nanogen_gui/_pyqt4_ui_graphene_generator.py
sknano/apps/nanogen_gui/_pyqt4_ui_mwnt_Ch_list_item_dialog.py
sknano/apps/nanogen_gui/_pyqt4_ui_mwnt_generator.py
sknano/apps/nanogen_gui/_pyqt4_ui_nanogen.py
sknano/apps/nanogen_gui/_pyqt4_ui_swnt_generator.py
sknano/apps/nanogen_gui/_pyqt5_ui_bulk_structure_generator.py
sknano/apps/nanogen_gui/_pyqt5_ui_fullerene_generator.py
sknano/apps/nanogen_gui/_pyqt5_ui_graphene_generator.py
sknano/apps/nanogen_gui/_pyqt5_ui_mwnt_Ch_list_item_dialog.py
