Metadata-Version: 1.1
Name: scikit-nano
Version: 0.3.18
Summary: Python toolkit for generating and analyzing nanostructure data
Home-page: http://scikit-nano.org/doc
Author: Andrew Merrill
Author-email: androomerrill@gmail.com
License: BSD 2-Clause
Download-URL: http://github.com/androomerrill/scikit-nano
Keywords: nano,nanoscience,nano-structure,nanostructure,nanotube,graphene,LAMMPS,XYZ,structure,analysis
Platform: Windows
Platform: Linux
Platform: Solaris
Platform: Mac OS-X
Platform: Unix
Classifier: Development Status :: 4 - Beta
Classifier: Intended Audience :: Science/Research
Classifier: Intended Audience :: Developers
Classifier: License :: OSI Approved :: BSD License
Classifier: Operating System :: Microsoft :: Windows
Classifier: Operating System :: POSIX
Classifier: Operating System :: Unix
Classifier: Operating System :: MacOS
Classifier: Programming Language :: Python
Classifier: Programming Language :: Python :: 3.4
Classifier: Topic :: Scientific/Engineering
Classifier: Topic :: Scientific/Engineering :: Chemistry
Classifier: Topic :: Scientific/Engineering :: Physics
Classifier: Topic :: Scientific/Engineering :: Visualization
Classifier: Topic :: Software Development
Classifier: Topic :: Software Development :: Libraries :: Python Modules
